Workbook

Sheet Instruções
A1: INSTRUÇÕES DE USO - CALCULADORA DE IMPRESSÃO 3D
A3: COMO USAR ESTA PLANILHA:
A5: 1. ABA CONFIGURAÇÕES:
A6: - Ajuste os preços dos materiais conforme necessário
A7: - Modifique o custo do kWh de energia elétrica
A8: - Atualize os preços das impressoras Bambu Lab
A9: - Configure a vida útil e horas de uso das impressoras
A10: - Defina as taxas de impostos e mão de obra
A12: 2. ABA CALCULADORA:
A13: - Digite o nome do produto
A14: - Selecione o material (PLA, PETG, ABS, NYLON, TPU)
A15: - Informe o peso do produto em gramas
... A50: - Ajuste margens conforme demanda

Sheet Configurações
A1: CONFIGURAÇÕES GERAIS
A3: ENERGIA | B3: Preço [R$/kWh]
A4: Custo por kWh (R$): | B4: 1.2
A6: MATERIAIS | B6: Preço [R$/kg]
A7: PLA | B7: 94.9
A8: PETG | B8: 94.9
A9: ABS | B9: 85
A10: NYLON | B10: 400
A11: TPU | B11: 220
A13: IMPRESSORAS BAMBU LAB | B13: Preço [R$]
A14: A1 MINI | B14: 2159
A15: A1 MINI COMBO | B15: 3824
A16: A1 | B16: 3284
A17: A1 COMBO | B17: 5039
A18: P1S | B18: 5800
A19: P1S COMBO | B19: 8774
A20: X1C | B20: 12554
A21: X1C COMBO | B21: 14624
A22: H2D | B22: 16100
A23: H2D COMBO | B23: 24299
A25: DEPRECIAÇÃO
A26: Vida útil (anos): | B26: 3
A27: Horas de uso por ano: | B27: 2000
A29: IMPOSTOS E TAXAS
A30: Taxa de imposto (%): | B30: 20
A32: MÃO DE OBRA
A33: Acréscimo mão de obra (%): | B33: 20

Sheet Calculadora
A1: CALCULADORA DE CUSTOS E PREÇOS - IMPRESSÃO 3D
E2: PREÇOS DE VENDA POR QUANTIDADE
A3: DADOS DO PRODUTO | B3: DADOS | E3: Quantidade | F3: Margem (%) | G3: Preço Unitário (R$) | H3: Preço Total (R$) | I3: Lucro Unitário (R$) | J3: Lucro Total (R$)
A4: Nome do produto: | B4: Chaveiro Kamila | E4: 1 | F4: 300 | G4: =$B$18*(1+F4/100) -> 13.67056 | H4: =G4*E4 -> 13.67056 | I4: =G4-$B$18 -> 10.25292 | J4: =I4*E4 -> 10.25292
A5: Material: | B5: PLA | E5: 5 | F5: 250 | G5: =$B$18*(1+F5/100) -> 11.96174 | H5: =G5*E5 -> 59.8087 | I5: =G5-$B$18 -> 8.5441 | J5: =I5*E5 -> 42.7205
A6: Peso do produto (g): | B6: 18 | E6: 10 | F6: 200 | G6: =$B$18*(1+F6/100) -> 10.25292 | H6: =G6*E6 -> 102.5292 | I6: =G6-$B$18 -> 6.83528 | J6: =I6*E6 -> 68.3528
A7: Tempo de impressão (horas): | B7: 1 | E7: 25 | F7: 150 | G7: =$B$18*(1+F7/100) -> 8.5441 | H7: =G7*E7 -> 213.6025 | I7: =G7-$B$18 -> 5.12646 | J7: =I7*E7 -> 128.1615
A8: Impressora utilizada: | B8: A1 COMBO | E8: 50 | F8: 120 | G8: =$B$18*(1+F8/100) -> 7.518808 | H8: =G8*E8 -> 375.9404 | I8: =G8-$B$18 -> 4.101168 | J8: =I8*E8 -> 205.0584
A9: Requer mão de obra? : | B9: SIM | E9: 100 | F9: 100 | G9: =$B$18*(1+F9/100) -> 6.83528 | H9: =G9*E9 -> 683.528 | I9: =G9-$B$18 -> 3.41764 | J9: =I9*E9 -> 341.764
A10: Quantidade de Impressoras | B10: 1 | E10: 500 | F10: 80 | G10: =$B$18*(1+F10/100) -> 6.151752 | H10: =G10*E10 -> 3075.876 | I10: =G10-$B$18 -> 2.734112 | J10: =I10*E10 -> 1367.056
E11: 1000 | F11: 70 | G11: =$B$18*(1+F11/100) -> 5.809988 | H11: =G11*E11 -> 5809.988 | I11: =G11-$B$18 -> 2.392348 | J11: =I11*E11 -> 2392.348
A12: CÁLCULOS DE CUSTO | B12: DADOS [R$] | E12: 2500 | F12: 60 | G12: =$B$18*(1+F12/100) -> 5.468224 | H12: =G12*E12 -> 13670.56 | I12: =G12-$B$18 -> 2.050584 | J12: =I12*E12 -> 5126.46
A13: Custo do material (R$): | B13: =B6/1000*VLOOKUP(B5,Configurações!$A$7:$B$11,2,FALSE) -> 1.7082
A14: Custo da energia (R$): | B14: =B7*0.25*Configurações!$B$4 -> 0.3
A15: Custo hora máquina (R$): | B15: =VLOOKUP(B8,Configurações!$A$14:$B$22,2,FALSE)/(Configurações!$B$26*Configurações!$B$27)*B7 -> 0.83983333
A16: Custo total base (R$): | B16: =B13+B14+B15 -> 2.8480333
A17: Custo com mão de obra (R$): | B17: =IF(B9="SIM",B16*(1+Configurações!$B$33/100),B16) -> 3.41764
A18: Custo final (R$): | B18: =B17 -> 3.41764
I19: IMPOSTOS
I20: Valor do imposto por unidade (R$): | J20: =B18*Configurações!$B$30/100 -> 0.683528

Sheet Impressão
C4: STEPHAN COMERCIO VAREJISTA LTDA
B9: =Calculadora!B4 -> Chaveiro Kamila
B12: Quant. De Peças | C12: Valor Unidade | D12: Prazo [Dia]
B13: =Calculadora!E4 -> 1 | C13: =Calculadora!G4 -> 13.67056 | D13: =ROUNDUP((Calculadora!B7+12)/24,0) -> 1
B14: =Calculadora!E5 -> 5 | C14: =Calculadora!G5 -> 11.96174 | D14: =ROUNDUP(((Calculadora!B7*B14+12)/Calculadora!B10)/24,0) -> 1
B15: =Calculadora!E6 -> 10 | C15: =Calculadora!G6 -> 10.25292 | D15: =ROUNDUP((Calculadora!B7*B15+12)/Calculadora!B10/24,0) -> 1
B16: =Calculadora!E7 -> 25 | C16: =Calculadora!G7 -> 8.5441 | D16: =ROUNDUP((Calculadora!B7*B16+12)/Calculadora!B10/24,0) -> 2
B17: =Calculadora!E8 -> 50 | C17: =Calculadora!G8 -> 7.518808 | D17: =ROUNDUP((Calculadora!B7*B17+12)/Calculadora!B10/24,0) -> 3
B18: =Calculadora!E9 -> 100 | C18: =Calculadora!G9 -> 6.83528 | D18: =ROUNDUP((Calculadora!B7*B18+12)/Calculadora!B10/24,0) -> 5
B19: =Calculadora!E10 -> 500 | C19: =Calculadora!G10 -> 6.151752 | D19: =ROUNDUP((Calculadora!B7*B19+12)/Calculadora!B10/24,0) -> 22
B20: =Calculadora!E11 -> 1000 | C20: =Calculadora!G11 -> 5.809988 | D20: =ROUNDUP((Calculadora!B7*B20+12)/Calculadora!B10/24,0) -> 43
B21: =Calculadora!E12 -> 2500 | C21: =Calculadora!G12 -> 5.468224 | D21: =ROUNDUP((Calculadora!B7*B21+12)/Calculadora!B10/24,0) -> 105

Sheet Análise de Custos
A1: ANÁLISE DETALHADA DE CUSTOS
A3: CUSTO HORA MÁQUINA POR IMPRESSORA
A4: Impressora | B4: Preço (R$) | C4: Custo/Hora (R$) | D4: Custo/Dia 8h (R$) | E4: Custo/Mês (R$)
A5: A1 MINI | B5: =Configurações!B14 -> 2159 | C5: =B5/(Configurações!$B$26*Configurações!$B$27) -> 0.35983333 | D5: =C5*8 -> 2.8786667 | E5: =D5*22 -> 63.330667
A6: A1 MINI COMBO | B6: =Configurações!B15 -> 3824 | C6: =B6/(Configurações!$B$26*Configurações!$B$27) -> 0.63733333 | D6: =C6*8 -> 5.0986667 | E6: =D6*22 -> 112.17067
A7: A1 | B7: =Configurações!B16 -> 3284 | C7: =B7/(Configurações!$B$26*Configurações!$B$27) -> 0.54733333 | D7: =C7*8 -> 4.3786667 | E7: =D7*22 -> 96.330667
A8: A1 COMBO | B8: =Configurações!B17 -> 5039 | C8: =B8/(Configurações!$B$26*Configurações!$B$27) -> 0.83983333 | D8: =C8*8 -> 6.7186667 | E8: =D8*22 -> 147.81067
A9: P1S | B9: =Configurações!B18 -> 5800 | C9: =B9/(Configurações!$B$26*Configurações!$B$27) -> 0.96666667 | D9: =C9*8 -> 7.7333333 | E9: =D9*22 -> 170.13333
A10: P1S COMBO | B10: =Configurações!B19 -> 8774 | C10: =B10/(Configurações!$B$26*Configurações!$B$27) -> 1.4623333 | D10: =C10*8 -> 11.698667 | E10: =D10*22 -> 257.37067
A11: X1C | B11: =Configurações!B20 -> 12554 | C11: =B11/(Configurações!$B$26*Configurações!$B$27) -> 2.0923333 | D11: =C11*8 -> 16.738667 | E11: =D11*22 -> 368.25067
A12: X1C COMBO | B12: =Configurações!B21 -> 14624 | C12: =B12/(Configurações!$B$26*Configurações!$B$27) -> 2.4373333 | D12: =C12*8 -> 19.498667 | E12: =D12*22 -> 428.97067
A13: H2D | B13: =Configurações!B22 -> 16100 | C13: =B13/(Configurações!$B$26*Configurações!$B$27) -> 2.6833333 | D13: =C13*8 -> 21.466667 | E13: =D13*22 -> 472.26667
A14: H2D COMBO | B14: =Configurações!B23 -> 24299 | C14: =B14/(Configurações!$B$26*Configurações!$B$27) -> 4.0498333 | D14: =C14*8 -> 32.398667 | E14: =D14*22 -> 712.77067
A16: CUSTO POR GRAMA DE MATERIAL
A17: Material | B17: Preço/kg (R$) | C17: Preço/g (R$) | D17: Custo 50g (R$) | E17: Custo 100g (R$)
A18: PLA | B18: 118.89 | C18: =B18/1000 -> 0.11889 | D18: =C18*50 -> 5.9445 | E18: =C18*100 -> 11.889
A19: PETG | B19: 134.99 | C19: =B19/1000 -> 0.13499 | D19: =C19*50 -> 6.7495 | E19: =C19*100 -> 13.499
A20: ABS | B20: 80 | C20: =B20/1000 -> 0.08 | D20: =C20*50 -> 4 | E20: =C20*100 -> 8
A21: NYLON | B21: 299.98 | C21: =B21/1000 -> 0.29998 | D21: =C21*50 -> 14.999 | E21: =C21*100 -> 29.998
A22: TPU | B22: 329.19 | C22: =B22/1000 -> 0.32919 | D22: =C22*50 -> 16.4595 | E22: =C22*100 -> 32.919
